{
  "synthetic": true,
  "status": "frozen",
  "freeze_id": "connector-implementation-roadmap-freeze-aion-115",
  "read_only": true,
  "design_only": true,
  "redaction_applied": true,
  "connector_runtime_enabled": false,
  "external_calls_enabled": false,
  "credentials_present": false,
  "token_storage_enabled": false,
  "sandbox_execution_enabled": false,
  "connector_activation_enabled": false,
  "route_registration_enabled": false,
  "implementation_approved": false,
  "release_gate_passed": true,
  "safety_freeze_passed": true,
  "package_files_added": false,
  "migrations_added": false,
  "provider_sdk_dependency_added": false,
  "api_runtime_execution_route_added": false,
  "endpoint_references_present": false,
  "secret_material_present": false,
  "credential_values_present": false,
  "token_values_present": false,
  "private_prompt_material_present": false,
  "private_reasoning_present": false,
  "future_requirements": [
    "explicit_adr",
    "production_auth_decision",
    "credential_design_implementation_approval",
    "sandbox_implementation_approval",
    "external_call_release_gate",
    "rollback_audit_plan",
    "operator_review_policy_enforcement"
  ],
  "created_at": "2026-06-30T00:00:00Z"
}
