{"activation_candidate_id":"candidate-181","activation_program_id":"AION-SELF-IMPROVEMENT-CONTROLLED-SHADOW-ACTIVATION-001","authorization_scope":"disabled-shadow-activation-request-approval-monitoring-deactivation-control-plane","authorization_transaction_id":"AION-180-SI-0007","created_at":"2026-07-20T16:00:00Z","evidence_preservation_required":true,"fingerprint":"48b16348801fa1cc2674ad63f21ecb19f7c1f9cb4042b35a3277ebdd5352e4dc","forbidden_counters_must_equal_zero":true,"formal_closeout_task":"AION-182","implementation_task":"AION-181","incident_record_required":true,"monitoring_plan_id":"monitoring-plan-181","operator_kill_switch_required":true,"program_id":"AION-SELF-IMPROVEMENT-001","read_only":true,"redacted":true,"required_metric_names":["run_count","reference_count","evaluation_count","pattern_count","hypothesis_count","regression_proposal_count","shadow_proposal_count","review_item_count","budget_violation_count","redaction_failure_count","reference_failure_count","fingerprint_mismatch_count","output_boundary_failure_count","wall_clock_seconds","benchmark_cost_units","output_bytes","output_files","network_call_count","connector_call_count","provider_call_count","git_operation_count","source_mutation_count","real_pr_count","approval_creation_count","runtime_promotion_count","runtime_influence_count"],"runtime_effect":false,"schema_version":"self-improvement-shadow-activation-monitoring/v1","shadow_activation_control_plane_authorized":true,"shadow_activation_control_plane_implemented":true,"shadow_activation_control_plane_state":"implemented_disabled_simulation_only","shadow_activation_enabled":false,"shadow_mode_runtime_enabled":false,"synthetic":true,"thresholds":[{"deactivate_on_breach":true,"fingerprint":"092d39d82b5248334c25323f25df8479bf3a34d80cd7349885b5020e7a840a7e","maximum_value":10000.0,"metric_name":"run_count","reason_code":"activation_monitoring_breached"},{"deactivate_on_breach":true,"fingerprint":"e0200f9ea2918296df3df4d17386ad0e74a898caae988acafdf029231213d055","maximum_value":10000.0,"metric_name":"reference_count","reason_code":"activation_monitoring_breached"},{"deactivate_on_breach":true,"fingerprint":"66d12cccf1af197d9c8c4b8855a692cae25ebfde0f72b93528f068f5616769f6","maximum_value":10000.0,"metric_name":"evaluation_count","reason_code":"activation_monitoring_breached"},{"deactivate_on_breach":true,"fingerprint":"5debe4e35a7460b74866c2a604258a41f3f91ad66927214959f7399740699a3e","maximum_value":10000.0,"metric_name":"pattern_count","reason_code":"activation_monitoring_breached"},{"deactivate_on_breach":true,"fingerprint":"8f7510eb0ee3027bd985cf2a3acdc6923892754c29ea08df899c1bb3a6322666","maximum_value":10000.0,"metric_name":"hypothesis_count","reason_code":"activation_monitoring_breached"},{"deactivate_on_breach":true,"fingerprint":"c677d3bd139b0a7a632e7f9c2f40a03309e58f87118928eebbb72dec0fa4af04","maximum_value":10000.0,"metric_name":"regression_proposal_count","reason_code":"activation_monitoring_breached"},{"deactivate_on_breach":true,"fingerprint":"bfd5e234262cc1b7f484ddb26977f999e9e7f5f3e2b8868ad83f5036143e7300","maximum_value":10000.0,"metric_name":"shadow_proposal_count","reason_code":"activation_monitoring_breached"},{"deactivate_on_breach":true,"fingerprint":"908bb32bf457b46b89b5c08fc8657045484e8ac2bb5418822c4510f5d8d47cae","maximum_value":10000.0,"metric_name":"review_item_count","reason_code":"activation_monitoring_breached"},{"deactivate_on_breach":true,"fingerprint":"043f0ad6645b39df5cbb8d15d487a33b98f2f556bef38321eaae4d632ba2d5f9","maximum_value":10000.0,"metric_name":"budget_violation_count","reason_code":"activation_monitoring_breached"},{"deactivate_on_breach":true,"fingerprint":"0f468bb74cee13a9df4f9f0866d7dbe058259c72d6d190bbab55c6f2343c5dc0","maximum_value":10000.0,"metric_name":"redaction_failure_count","reason_code":"activation_monitoring_breached"},{"deactivate_on_breach":true,"fingerprint":"e2f28d7e23b06da0bafd135eff7bb6c2db400338eff954e0bc586d4d9ffdb8a3","maximum_value":10000.0,"metric_name":"reference_failure_count","reason_code":"activation_monitoring_breached"},{"deactivate_on_breach":true,"fingerprint":"b37875771ed9495bfb441eee3b895ff21f85825c91326e3e3937f72d9070392d","maximum_value":10000.0,"metric_name":"fingerprint_mismatch_count","reason_code":"activation_monitoring_breached"},{"deactivate_on_breach":true,"fingerprint":"6f59a06d837fbd44caf9fade7a33f3bf55beaadadc790be0e639d5a582ee0664","maximum_value":10000.0,"metric_name":"output_boundary_failure_count","reason_code":"activation_monitoring_breached"},{"deactivate_on_breach":true,"fingerprint":"a4f2a252bb823c9d22918de2ee2331d6c9ad9c28f2d7dcc30c219b9b866134f3","maximum_value":10000.0,"metric_name":"wall_clock_seconds","reason_code":"activation_monitoring_breached"},{"deactivate_on_breach":true,"fingerprint":"a36375bfd3ed2db06b1802b7e5a2ad4bea2455cbf16879604fc09b7067339ef2","maximum_value":10000.0,"metric_name":"benchmark_cost_units","reason_code":"activation_monitoring_breached"},{"deactivate_on_breach":true,"fingerprint":"54c0f8b096978894a8ed8a185423193df9a0bb7e344a834187b3310fe43185a9","maximum_value":10000.0,"metric_name":"output_bytes","reason_code":"activation_monitoring_breached"},{"deactivate_on_breach":true,"fingerprint":"8430e7b21942962224bcc97d7b202b0eadd23940fcbcd89d40c360678167fc93","maximum_value":10000.0,"metric_name":"output_files","reason_code":"activation_monitoring_breached"},{"deactivate_on_breach":true,"fingerprint":"65d14322026bdbdd20896c78bc59b183b91fbfb7c1dc5073f3541b82840d448d","maximum_value":0.0,"metric_name":"network_call_count","reason_code":"activation_monitoring_breached"},{"deactivate_on_breach":true,"fingerprint":"584d83ae9acbb1a163a7c10304a80dc34fa5e3a997f404d155bdfacddaa62379","maximum_value":0.0,"metric_name":"connector_call_count","reason_code":"activation_monitoring_breached"},{"deactivate_on_breach":true,"fingerprint":"864a29c59082b032445955d771a1114a2da87dddafe1b27059c9157634c74d59","maximum_value":0.0,"metric_name":"provider_call_count","reason_code":"activation_monitoring_breached"},{"deactivate_on_breach":true,"fingerprint":"4c9ed19d513c593a141f118ec29b674f0c4267fc8674e5c68a9a0879b2cd15a8","maximum_value":0.0,"metric_name":"git_operation_count","reason_code":"activation_monitoring_breached"},{"deactivate_on_breach":true,"fingerprint":"a83ab03ddbf3a1c8ca63dd2af65fce2defd3aa1d69b9c8724d6581aa3c0da313","maximum_value":0.0,"metric_name":"source_mutation_count","reason_code":"activation_monitoring_breached"},{"deactivate_on_breach":true,"fingerprint":"9966e9c9ae1dfee984df140ffabdab7b1efb8e52353fe6df3347469f435c8bcd","maximum_value":0.0,"metric_name":"real_pr_count","reason_code":"activation_monitoring_breached"},{"deactivate_on_breach":true,"fingerprint":"f015d8bc2fcfda2b8a5b866cdc353a4a53fc32c7c8175dd2c7d4d9f94973b9bb","maximum_value":0.0,"metric_name":"approval_creation_count","reason_code":"activation_monitoring_breached"},{"deactivate_on_breach":true,"fingerprint":"b65608a8f167dbb2b030c749c38e757d9adb161e0278e749295bfc5d92ffb330","maximum_value":0.0,"metric_name":"runtime_promotion_count","reason_code":"activation_monitoring_breached"},{"deactivate_on_breach":true,"fingerprint":"8f1a654de3d6af7d5c099a85f41a1da0d5c86180939ea1b8c4fa4e402bb25de1","maximum_value":0.0,"metric_name":"runtime_influence_count","reason_code":"activation_monitoring_breached"}]}
